douki/__init__.py
douki/_validation.py
douki/core.py
douki/py.typed
douki/schema.json
douki-0.6.0.dist-info/METADATA
douki-0.6.0.dist-info/WHEEL
douki-0.6.0.dist-info/licenses/LICENSE
douki-0.6.0.dist-info/RECORD
