Metadata-Version: 2.4
Name: douki
Version: 0.6.0
Summary: Documetatio from annotations
License: BSD 3 Clause
License-File: LICENSE
Author: Ivan Ogasawara
Author-email: ivan.ogasawara@gmail.com
Requires-Python: >=3.9,<4
Classifier: License :: Other/Proprietary License
Classifier: Programming Language :: Python :: 3
Classifier: Programming Language :: Python :: 3.9
Classifier: Programming Language :: Python :: 3.10
Classifier: Programming Language :: Python :: 3.11
Classifier: Programming Language :: Python :: 3.12
Classifier: Programming Language :: Python :: 3.13
Classifier: Programming Language :: Python :: 3.14
Requires-Dist: types-pyyaml (>=6)
Requires-Dist: typing-extensions (>=4.14.1)
